clockitpy/__init__.py
clockitpy/timer.py
clockitpy-0.1.0.dist-info/licenses/LICENSE
clockitpy-0.1.0.dist-info/METADATA
clockitpy-0.1.0.dist-info/WHEEL
clockitpy-0.1.0.dist-info/top_level.txt
clockitpy-0.1.0.dist-info/RECORD
