Metadata-Version: 2.4
Name: clockitpy
Version: 0.1.0
Summary: A lightweight Python library to measure function execution time.
Home-page: 
Author: Unknon Man
Author-email: unknonmanbro@gamil.com
License: MIT
Requires-Python: >=3.7
License-File: LICENSE
Dynamic: author
Dynamic: author-email
Dynamic: description
Dynamic: description-content-type
Dynamic: license
Dynamic: license-file
Dynamic: requires-python
Dynamic: summary
